py2eviews/__init__.py
py2eviews-1.0.7.dist-info/LICENSE.txt
py2eviews-1.0.7.dist-info/METADATA
py2eviews-1.0.7.dist-info/WHEEL
py2eviews-1.0.7.dist-info/top_level.txt
py2eviews-1.0.7.dist-info/RECORD
