Metadata-Version: 2.1
Name: py2eviews
Version: 1.0.7
Summary: Data import/export and EViews function calls from Python
Home-page: https://github.com/eviews-support/py2eviews
Author: EViews-Support
Author-email: support@eviews.com
License: GPLv3
Keywords: eviews econometrics
Classifier: Development Status :: 5 - Production/Stable
Classifier: License :: OSI Approved :: GNU General Public License v3 (GPLv3)
Classifier: Topic :: Scientific/Engineering :: Information Analysis
Classifier: Programming Language :: Python :: 3
Classifier: Operating System :: Microsoft :: Windows
License-File: LICENSE.txt
Requires-Dist: comtypes
Requires-Dist: numpy
Requires-Dist: pandas
